[
  {
    "path": "C:\\Users\\user\\Downloads\\Florida's GEOLOGICAL Nightmare",
    "name": "Florida's GEOLOGICAL Nightmare",
    "lastOpened": "2026-03-02T16:12:33.872Z"
  },
  {
    "path": "C:\\Users\\user\\Downloads\\LNG Panic — Qatar Signals Supply Shift",
    "name": "LNG Panic — Qatar Signals Supply Shift",
    "lastOpened": "2026-03-02T14:58:25.328Z"
  },
  {
    "path": "C:\\Users\\user\\Downloads\\test canvas new mgs",
    "name": "test canvas new mgs",
    "lastOpened": "2026-02-28T23:09:25.511Z"
  },
  {
    "path": "C:\\Users\\user\\Downloads\\AI drone video 9min",
    "name": "AI drone video 9min",
    "lastOpened": "2026-02-27T16:34:03.366Z"
  },
  {
    "path": "C:\\Users\\user\\Downloads\\ocean discovery",
    "name": "ocean discovery",
    "lastOpened": "2026-02-27T15:54:30.047Z"
  },
  {
    "path": "C:\\Users\\user\\Downloads\\Canada REJECTS New U.S. Lumber Tariffs",
    "name": "Canada REJECTS New U.S. Lumber Tariffs",
    "lastOpened": "2026-02-27T15:10:55.644Z"
  },
  {
    "path": "C:\\Users\\user\\Downloads\\Windows is done",
    "name": "Windows is done",
    "lastOpened": "2026-02-27T00:59:40.541Z"
  },
  {
    "path": "C:\\Users\\user\\Downloads\\Sammy Davis",
    "name": "Sammy Davis",
    "lastOpened": "2026-02-26T21:38:49.434Z"
  },
  {
    "path": "C:\\Users\\user\\Downloads\\australia tomato to avoid",
    "name": "australia tomato to avoid",
    "lastOpened": "2026-02-26T00:49:08.888Z"
  },
  {
    "path": "C:\\Users\\user\\Downloads\\zeeker mix china car",
    "name": "zeeker mix china car",
    "lastOpened": "2026-02-25T23:29:23.732Z"
  },
  {
    "path": "C:\\Users\\user\\Downloads\\Malysia Earthqueque",
    "name": "Malysia Earthqueque",
    "lastOpened": "2026-02-25T23:04:41.198Z"
  },
  {
    "path": "C:\\Users\\user\\Downloads\\five dim store",
    "name": "five dim store",
    "lastOpened": "2026-02-25T22:26:45.667Z"
  },
  {
    "path": "C:\\Users\\user\\Downloads\\Canada vs USA",
    "name": "Canada vs USA",
    "lastOpened": "2026-02-25T21:58:55.093Z"
  },
  {
    "path": "C:\\Users\\user\\Downloads\\iran vs usa",
    "name": "iran vs usa",
    "lastOpened": "2026-02-25T21:16:41.513Z"
  },
  {
    "path": "C:\\Users\\user\\Downloads\\ibraham lincol dna",
    "name": "ibraham lincol dna",
    "lastOpened": "2026-02-25T16:29:17.277Z"
  },
  {
    "path": "C:\\Users\\user\\Downloads\\canada can't build",
    "name": "canada can't build",
    "lastOpened": "2026-02-25T16:01:32.395Z"
  },
  {
    "path": "C:\\Users\\user\\Downloads\\china taxis",
    "name": "china taxis",
    "lastOpened": "2026-02-25T15:43:11.843Z"
  },
  {
    "path": "C:\\Users\\user\\Downloads\\1dollar Toy",
    "name": "1dollar Toy",
    "lastOpened": "2026-02-25T15:02:07.532Z"
  },
  {
    "path": "C:\\Users\\user\\Downloads\\sign from god",
    "name": "sign from god",
    "lastOpened": "2026-02-25T11:48:03.201Z"
  },
  {
    "path": "D:\\Youtube\\faceless-app",
    "name": "faceless-app",
    "lastOpened": "2026-02-24T13:30:27.894Z"
  }
]